core/__main__.py
inf_ipy-0.1.103.dist-info/METADATA
inf_ipy-0.1.103.dist-info/WHEEL
inf_ipy-0.1.103.dist-info/entry_points.txt
inf_ipy-0.1.103.dist-info/top_level.txt
inf_ipy-0.1.103.dist-info/RECORD
